{"id":232,"dbSymbol":"donphan","forms":[{"form":0,"height":1.1,"weight":120.0,"type1":"ground","type2":"__undef__","baseHp":90,"baseAtk":120,"baseDfe":120,"baseSpd":50,"baseAts":60,"baseDfs":60,"evHp":0,"evAtk":1,"evDfe":1,"evSpd":0,"evAts":0,"evDfs":0,"evolutions":[],"experienceType":1,"baseExperience":175,"baseLoyalty":70,"catchRate":60,"femaleRate":50,"breedGroups":[5,5],"hatchSteps":5120,"babyDbSymbol":"phanpy","babyForm":0,"itemHeld":[],"abilities":["sturdy","sturdy","sand_veil"],"frontOffsetY":24,"moveSet":[{"klass":"LevelLearnableMove","level":1,"move":"fire_fang"},{"klass":"LevelLearnableMove","level":1,"move":"thunder_fang"},{"klass":"LevelLearnableMove","level":1,"move":"horn_attack"},{"klass":"LevelLearnableMove","level":1,"move":"bulldoze"},{"klass":"LevelLearnableMove","level":1,"move":"growl"},{"klass":"LevelLearnableMove","level":1,"move":"defense_curl"},{"klass":"LevelLearnableMove","level":6,"move":"rapid_spin"},{"klass":"LevelLearnableMove","level":10,"move":"rollout"},{"klass":"LevelLearnableMove","level":15,"move":"assurance"},{"klass":"LevelLearnableMove","level":19,"move":"knock_off"},{"klass":"LevelLearnableMove","level":24,"move":"slam"},{"klass":"LevelLearnableMove","level":25,"move":"fury_attack"},{"klass":"LevelLearnableMove","level":30,"move":"magnitude"},{"klass":"LevelLearnableMove","level":37,"move":"scary_face"},{"klass":"LevelLearnableMove","level":43,"move":"earthquake"},{"klass":"LevelLearnableMove","level":50,"move":"giga_impact"},{"klass":"TutorLearnableMove","move":"snore"},{"klass":"TutorLearnableMove","move":"iron_tail"},{"klass":"TutorLearnableMove","move":"superpower"},{"klass":"TutorLearnableMove","move":"knock_off"},{"klass":"TutorLearnableMove","move":"endeavor"},{"klass":"TutorLearnableMove","move":"hyper_voice"},{"klass":"TutorLearnableMove","move":"iron_defense"},{"klass":"TutorLearnableMove","move":"block"},{"klass":"TutorLearnableMove","move":"bounce"},{"klass":"TutorLearnableMove","move":"last_resort"},{"klass":"TutorLearnableMove","move":"seed_bomb"},{"klass":"TutorLearnableMove","move":"earth_power"},{"klass":"TutorLearnableMove","move":"gunk_shot"},{"klass":"TutorLearnableMove","move":"stealth_rock"},{"klass":"TechLearnableMove","move":"roar"},{"klass":"TechLearnableMove","move":"hyper_beam"},{"klass":"TechLearnableMove","move":"strength"},{"klass":"TechLearnableMove","move":"earthquake"},{"klass":"TechLearnableMove","move":"toxic"},{"klass":"TechLearnableMove","move":"double_team"},{"klass":"TechLearnableMove","move":"rest"},{"klass":"TechLearnableMove","move":"rock_slide"},{"klass":"TechLearnableMove","move":"substitute"},{"klass":"TechLearnableMove","move":"protect"},{"klass":"TechLearnableMove","move":"sandstorm"},{"klass":"TechLearnableMove","move":"swagger"},{"klass":"TechLearnableMove","move":"attract"},{"klass":"TechLearnableMove","move":"sleep_talk"},{"klass":"TechLearnableMove","move":"return"},{"klass":"TechLearnableMove","move":"frustration"},{"klass":"TechLearnableMove","move":"hidden_power"},{"klass":"TechLearnableMove","move":"sunny_day"},{"klass":"TechLearnableMove","move":"rock_smash"},{"klass":"TechLearnableMove","move":"facade"},{"klass":"TechLearnableMove","move":"secret_power"},{"klass":"TechLearnableMove","move":"rock_tomb"},{"klass":"TechLearnableMove","move":"gyro_ball"},{"klass":"TechLearnableMove","move":"rock_polish"},{"klass":"TechLearnableMove","move":"poison_jab"},{"klass":"TechLearnableMove","move":"giga_impact"},{"klass":"TechLearnableMove","move":"stone_edge"},{"klass":"TechLearnableMove","move":"round"},{"klass":"TechLearnableMove","move":"echoed_voice"},{"klass":"TechLearnableMove","move":"bulldoze"},{"klass":"TechLearnableMove","move":"confide"}]}],"klass":"Specie"}