{"id":680,"dbSymbol":"doublade","forms":[{"form":0,"height":0.8,"weight":4.5,"type1":"steel","type2":"ghost","baseHp":59,"baseAtk":110,"baseDfe":150,"baseSpd":35,"baseAts":45,"baseDfs":49,"evHp":0,"evAtk":0,"evDfe":2,"evSpd":0,"evAts":0,"evDfs":0,"evolutions":[{"conditions":[{"type":"stone","value":"dusk_stone"}],"dbSymbol":"aegislash","form":0}],"experienceType":1,"baseExperience":157,"baseLoyalty":70,"catchRate":90,"femaleRate":50,"breedGroups":[10,10],"hatchSteps":5120,"babyDbSymbol":"honedge","babyForm":0,"itemHeld":[],"abilities":["no_guard","no_guard","no_guard"],"frontOffsetY":13,"moveSet":[{"klass":"LevelLearnableMove","level":1,"move":"tackle"},{"klass":"LevelLearnableMove","level":1,"move":"swords_dance"},{"klass":"LevelLearnableMove","level":5,"move":"fury_cutter"},{"klass":"LevelLearnableMove","level":8,"move":"metal_sound"},{"klass":"LevelLearnableMove","level":13,"move":"pursuit"},{"klass":"LevelLearnableMove","level":18,"move":"autotomize"},{"klass":"LevelLearnableMove","level":20,"move":"shadow_sneak"},{"klass":"LevelLearnableMove","level":22,"move":"aerial_ace"},{"klass":"LevelLearnableMove","level":26,"move":"retaliate"},{"klass":"LevelLearnableMove","level":29,"move":"slash"},{"klass":"LevelLearnableMove","level":32,"move":"iron_defense"},{"klass":"LevelLearnableMove","level":36,"move":"night_slash"},{"klass":"LevelLearnableMove","level":41,"move":"power_trick"},{"klass":"LevelLearnableMove","level":45,"move":"iron_head"},{"klass":"LevelLearnableMove","level":51,"move":"sacred_sword"},{"klass":"TutorLearnableMove","move":"snore"},{"klass":"TutorLearnableMove","move":"spite"},{"klass":"TutorLearnableMove","move":"iron_defense"},{"klass":"TutorLearnableMove","move":"shock_wave"},{"klass":"TutorLearnableMove","move":"magnet_rise"},{"klass":"TutorLearnableMove","move":"iron_head"},{"klass":"TutorLearnableMove","move":"after_you"},{"klass":"TechLearnableMove","move":"swords_dance"},{"klass":"TechLearnableMove","move":"cut"},{"klass":"TechLearnableMove","move":"toxic"},{"klass":"TechLearnableMove","move":"double_team"},{"klass":"TechLearnableMove","move":"reflect"},{"klass":"TechLearnableMove","move":"rest"},{"klass":"TechLearnableMove","move":"rock_slide"},{"klass":"TechLearnableMove","move":"substitute"},{"klass":"TechLearnableMove","move":"protect"},{"klass":"TechLearnableMove","move":"false_swipe"},{"klass":"TechLearnableMove","move":"swagger"},{"klass":"TechLearnableMove","move":"attract"},{"klass":"TechLearnableMove","move":"sleep_talk"},{"klass":"TechLearnableMove","move":"return"},{"klass":"TechLearnableMove","move":"frustration"},{"klass":"TechLearnableMove","move":"hidden_power"},{"klass":"TechLearnableMove","move":"rain_dance"},{"klass":"TechLearnableMove","move":"rock_smash"},{"klass":"TechLearnableMove","move":"facade"},{"klass":"TechLearnableMove","move":"brick_break"},{"klass":"TechLearnableMove","move":"secret_power"},{"klass":"TechLearnableMove","move":"aerial_ace"},{"klass":"TechLearnableMove","move":"gyro_ball"},{"klass":"TechLearnableMove","move":"shadow_claw"},{"klass":"TechLearnableMove","move":"flash_cannon"},{"klass":"TechLearnableMove","move":"retaliate"},{"klass":"TechLearnableMove","move":"confide"}]}],"klass":"Specie"}