{"id":368,"dbSymbol":"gorebyss","forms":[{"form":0,"height":1.8,"weight":22.6,"type1":"water","type2":"__undef__","baseHp":55,"baseAtk":84,"baseDfe":105,"baseSpd":52,"baseAts":114,"baseDfs":75,"evHp":0,"evAtk":0,"evDfe":0,"evSpd":0,"evAts":2,"evDfs":0,"evolutions":[],"experienceType":4,"baseExperience":170,"baseLoyalty":70,"catchRate":60,"femaleRate":50,"breedGroups":[2,2],"hatchSteps":5120,"babyDbSymbol":"clamperl","babyForm":0,"itemHeld":[],"abilities":["swift_swim","swift_swim","hydration"],"frontOffsetY":22,"moveSet":[{"klass":"LevelLearnableMove","level":1,"move":"whirlpool"},{"klass":"LevelLearnableMove","level":1,"move":"confusion"},{"klass":"LevelLearnableMove","level":5,"move":"water_sport"},{"klass":"LevelLearnableMove","level":9,"move":"agility"},{"klass":"LevelLearnableMove","level":11,"move":"draining_kiss"},{"klass":"LevelLearnableMove","level":14,"move":"water_pulse"},{"klass":"LevelLearnableMove","level":16,"move":"amnesia"},{"klass":"LevelLearnableMove","level":19,"move":"aqua_ring"},{"klass":"LevelLearnableMove","level":23,"move":"captivate"},{"klass":"LevelLearnableMove","level":26,"move":"dive"},{"klass":"LevelLearnableMove","level":29,"move":"baton_pass"},{"klass":"LevelLearnableMove","level":34,"move":"psychic"},{"klass":"LevelLearnableMove","level":39,"move":"aqua_tail"},{"klass":"LevelLearnableMove","level":45,"move":"coil"},{"klass":"LevelLearnableMove","level":50,"move":"hydro_pump"},{"klass":"TutorLearnableMove","move":"bind"},{"klass":"TutorLearnableMove","move":"snore"},{"klass":"TutorLearnableMove","move":"icy_wind"},{"klass":"TutorLearnableMove","move":"signal_beam"},{"klass":"TutorLearnableMove","move":"bounce"},{"klass":"TutorLearnableMove","move":"water_pulse"},{"klass":"TutorLearnableMove","move":"aqua_tail"},{"klass":"TechLearnableMove","move":"surf"},{"klass":"TechLearnableMove","move":"ice_beam"},{"klass":"TechLearnableMove","move":"blizzard"},{"klass":"TechLearnableMove","move":"hyper_beam"},{"klass":"TechLearnableMove","move":"toxic"},{"klass":"TechLearnableMove","move":"psychic"},{"klass":"TechLearnableMove","move":"double_team"},{"klass":"TechLearnableMove","move":"waterfall"},{"klass":"TechLearnableMove","move":"rest"},{"klass":"TechLearnableMove","move":"substitute"},{"klass":"TechLearnableMove","move":"protect"},{"klass":"TechLearnableMove","move":"swagger"},{"klass":"TechLearnableMove","move":"attract"},{"klass":"TechLearnableMove","move":"sleep_talk"},{"klass":"TechLearnableMove","move":"return"},{"klass":"TechLearnableMove","move":"frustration"},{"klass":"TechLearnableMove","move":"safeguard"},{"klass":"TechLearnableMove","move":"hidden_power"},{"klass":"TechLearnableMove","move":"rain_dance"},{"klass":"TechLearnableMove","move":"psych_up"},{"klass":"TechLearnableMove","move":"shadow_ball"},{"klass":"TechLearnableMove","move":"hail"},{"klass":"TechLearnableMove","move":"facade"},{"klass":"TechLearnableMove","move":"secret_power"},{"klass":"TechLearnableMove","move":"dive"},{"klass":"TechLearnableMove","move":"giga_impact"},{"klass":"TechLearnableMove","move":"round"},{"klass":"TechLearnableMove","move":"scald"},{"klass":"TechLearnableMove","move":"confide"},{"klass":"TechLearnableMove","move":"infestation"}]}],"klass":"Specie"}