{"id":174,"dbSymbol":"igglybuff","forms":[{"form":0,"height":0.3,"weight":1.0,"type1":"normal","type2":"fairy","baseHp":90,"baseAtk":30,"baseDfe":15,"baseSpd":15,"baseAts":40,"baseDfs":20,"evHp":1,"evAtk":0,"evDfe":0,"evSpd":0,"evAts":0,"evDfs":0,"evolutions":[{"conditions":[{"type":"minLoyalty","value":220}],"dbSymbol":"jigglypuff","form":0}],"experienceType":0,"baseExperience":42,"baseLoyalty":70,"catchRate":170,"femaleRate":75,"breedGroups":[15,15],"hatchSteps":2560,"babyDbSymbol":"__undef__","babyForm":0,"itemHeld":[],"abilities":["cute_charm","competitive","friend_guard"],"frontOffsetY":32,"moveSet":[{"klass":"LevelLearnableMove","level":1,"move":"sing"},{"klass":"LevelLearnableMove","level":1,"move":"charm"},{"klass":"LevelLearnableMove","level":3,"move":"defense_curl"},{"klass":"LevelLearnableMove","level":5,"move":"pound"},{"klass":"LevelLearnableMove","level":9,"move":"sweet_kiss"},{"klass":"LevelLearnableMove","level":11,"move":"copycat"},{"klass":"TutorLearnableMove","move":"snore"},{"klass":"TutorLearnableMove","move":"icy_wind"},{"klass":"TutorLearnableMove","move":"heal_bell"},{"klass":"TutorLearnableMove","move":"pain_split"},{"klass":"TutorLearnableMove","move":"uproar"},{"klass":"TutorLearnableMove","move":"helping_hand"},{"klass":"TutorLearnableMove","move":"role_play"},{"klass":"TutorLearnableMove","move":"magic_coat"},{"klass":"TutorLearnableMove","move":"recycle"},{"klass":"TutorLearnableMove","move":"endeavor"},{"klass":"TutorLearnableMove","move":"hyper_voice"},{"klass":"TutorLearnableMove","move":"bounce"},{"klass":"TutorLearnableMove","move":"covet"},{"klass":"TutorLearnableMove","move":"shock_wave"},{"klass":"TutorLearnableMove","move":"water_pulse"},{"klass":"TutorLearnableMove","move":"gravity"},{"klass":"TutorLearnableMove","move":"last_resort"},{"klass":"TechLearnableMove","move":"flamethrower"},{"klass":"TechLearnableMove","move":"solar_beam"},{"klass":"TechLearnableMove","move":"thunder_wave"},{"klass":"TechLearnableMove","move":"dig"},{"klass":"TechLearnableMove","move":"toxic"},{"klass":"TechLearnableMove","move":"psychic"},{"klass":"TechLearnableMove","move":"double_team"},{"klass":"TechLearnableMove","move":"light_screen"},{"klass":"TechLearnableMove","move":"reflect"},{"klass":"TechLearnableMove","move":"fire_blast"},{"klass":"TechLearnableMove","move":"dream_eater"},{"klass":"TechLearnableMove","move":"flash"},{"klass":"TechLearnableMove","move":"rest"},{"klass":"TechLearnableMove","move":"substitute"},{"klass":"TechLearnableMove","move":"protect"},{"klass":"TechLearnableMove","move":"swagger"},{"klass":"TechLearnableMove","move":"attract"},{"klass":"TechLearnableMove","move":"sleep_talk"},{"klass":"TechLearnableMove","move":"return"},{"klass":"TechLearnableMove","move":"frustration"},{"klass":"TechLearnableMove","move":"safeguard"},{"klass":"TechLearnableMove","move":"hidden_power"},{"klass":"TechLearnableMove","move":"rain_dance"},{"klass":"TechLearnableMove","move":"sunny_day"},{"klass":"TechLearnableMove","move":"psych_up"},{"klass":"TechLearnableMove","move":"shadow_ball"},{"klass":"TechLearnableMove","move":"facade"},{"klass":"TechLearnableMove","move":"secret_power"},{"klass":"TechLearnableMove","move":"fling"},{"klass":"TechLearnableMove","move":"grass_knot"},{"klass":"TechLearnableMove","move":"round"},{"klass":"TechLearnableMove","move":"echoed_voice"},{"klass":"TechLearnableMove","move":"incinerate"},{"klass":"TechLearnableMove","move":"wild_charge"},{"klass":"TechLearnableMove","move":"confide"},{"klass":"BreedLearnableMove","move":"feint_attack"},{"klass":"BreedLearnableMove","move":"perish_song"},{"klass":"BreedLearnableMove","move":"sleep_talk"},{"klass":"BreedLearnableMove","move":"present"},{"klass":"BreedLearnableMove","move":"wish"},{"klass":"BreedLearnableMove","move":"fake_tears"},{"klass":"BreedLearnableMove","move":"covet"},{"klass":"BreedLearnableMove","move":"gravity"},{"klass":"BreedLearnableMove","move":"punishment"},{"klass":"BreedLearnableMove","move":"last_resort"},{"klass":"BreedLearnableMove","move":"captivate"},{"klass":"BreedLearnableMove","move":"heal_pulse"},{"klass":"BreedLearnableMove","move":"misty_terrain"}]}],"klass":"Specie"}