{"id":473,"dbSymbol":"mamoswine","forms":[{"form":0,"height":2.5,"weight":291.0,"type1":"ice","type2":"ground","baseHp":110,"baseAtk":130,"baseDfe":80,"baseSpd":80,"baseAts":70,"baseDfs":60,"evHp":0,"evAtk":3,"evDfe":0,"evSpd":0,"evAts":0,"evDfs":0,"evolutions":[],"experienceType":2,"baseExperience":239,"baseLoyalty":70,"catchRate":50,"femaleRate":50,"breedGroups":[5,5],"hatchSteps":5120,"babyDbSymbol":"swinub","babyForm":0,"itemHeld":[],"abilities":["oblivious","snow_cloak","thick_fat"],"frontOffsetY":13,"moveSet":[{"klass":"LevelLearnableMove","level":1,"move":"scary_face"},{"klass":"LevelLearnableMove","level":1,"move":"ancient_power"},{"klass":"LevelLearnableMove","level":1,"move":"peck"},{"klass":"LevelLearnableMove","level":1,"move":"odor_sleuth"},{"klass":"LevelLearnableMove","level":1,"move":"mud_sport"},{"klass":"LevelLearnableMove","level":1,"move":"powder_snow"},{"klass":"LevelLearnableMove","level":5,"move":"mud_sport"},{"klass":"LevelLearnableMove","level":8,"move":"powder_snow"},{"klass":"LevelLearnableMove","level":11,"move":"mud_slap"},{"klass":"LevelLearnableMove","level":14,"move":"endure"},{"klass":"LevelLearnableMove","level":18,"move":"mud_bomb"},{"klass":"LevelLearnableMove","level":21,"move":"hail"},{"klass":"LevelLearnableMove","level":24,"move":"ice_fang"},{"klass":"LevelLearnableMove","level":28,"move":"take_down"},{"klass":"LevelLearnableMove","level":33,"move":"double_hit"},{"klass":"LevelLearnableMove","level":37,"move":"mist"},{"klass":"LevelLearnableMove","level":41,"move":"thrash"},{"klass":"LevelLearnableMove","level":46,"move":"earthquake"},{"klass":"LevelLearnableMove","level":52,"move":"blizzard"},{"klass":"LevelLearnableMove","level":58,"move":"scary_face"},{"klass":"TutorLearnableMove","move":"snore"},{"klass":"TutorLearnableMove","move":"icy_wind"},{"klass":"TutorLearnableMove","move":"superpower"},{"klass":"TutorLearnableMove","move":"knock_off"},{"klass":"TutorLearnableMove","move":"endeavor"},{"klass":"TutorLearnableMove","move":"block"},{"klass":"TutorLearnableMove","move":"earth_power"},{"klass":"TutorLearnableMove","move":"iron_head"},{"klass":"TutorLearnableMove","move":"stealth_rock"},{"klass":"TechLearnableMove","move":"roar"},{"klass":"TechLearnableMove","move":"ice_beam"},{"klass":"TechLearnableMove","move":"blizzard"},{"klass":"TechLearnableMove","move":"hyper_beam"},{"klass":"TechLearnableMove","move":"strength"},{"klass":"TechLearnableMove","move":"earthquake"},{"klass":"TechLearnableMove","move":"dig"},{"klass":"TechLearnableMove","move":"toxic"},{"klass":"TechLearnableMove","move":"double_team"},{"klass":"TechLearnableMove","move":"light_screen"},{"klass":"TechLearnableMove","move":"reflect"},{"klass":"TechLearnableMove","move":"rest"},{"klass":"TechLearnableMove","move":"rock_slide"},{"klass":"TechLearnableMove","move":"substitute"},{"klass":"TechLearnableMove","move":"protect"},{"klass":"TechLearnableMove","move":"sandstorm"},{"klass":"TechLearnableMove","move":"swagger"},{"klass":"TechLearnableMove","move":"attract"},{"klass":"TechLearnableMove","move":"sleep_talk"},{"klass":"TechLearnableMove","move":"return"},{"klass":"TechLearnableMove","move":"frustration"},{"klass":"TechLearnableMove","move":"hidden_power"},{"klass":"TechLearnableMove","move":"rain_dance"},{"klass":"TechLearnableMove","move":"rock_smash"},{"klass":"TechLearnableMove","move":"hail"},{"klass":"TechLearnableMove","move":"facade"},{"klass":"TechLearnableMove","move":"secret_power"},{"klass":"TechLearnableMove","move":"rock_tomb"},{"klass":"TechLearnableMove","move":"giga_impact"},{"klass":"TechLearnableMove","move":"stone_edge"},{"klass":"TechLearnableMove","move":"round"},{"klass":"TechLearnableMove","move":"bulldoze"},{"klass":"TechLearnableMove","move":"confide"}]}],"klass":"Specie"}