{"id":183,"dbSymbol":"marill","forms":[{"form":0,"height":0.4,"weight":8.5,"type1":"water","type2":"fairy","baseHp":70,"baseAtk":20,"baseDfe":50,"baseSpd":40,"baseAts":20,"baseDfs":50,"evHp":2,"evAtk":0,"evDfe":0,"evSpd":0,"evAts":0,"evDfs":0,"evolutions":[{"conditions":[{"type":"minLevel","value":20}],"dbSymbol":"azumarill","form":0}],"experienceType":0,"baseExperience":88,"baseLoyalty":70,"catchRate":190,"femaleRate":50,"breedGroups":[2,6],"hatchSteps":2560,"babyDbSymbol":"marill","babyForm":0,"itemHeld":[],"abilities":["huge_power","thick_fat","sap_sipper"],"frontOffsetY":31,"moveSet":[{"klass":"LevelLearnableMove","level":1,"move":"tackle"},{"klass":"LevelLearnableMove","level":1,"move":"water_gun"},{"klass":"LevelLearnableMove","level":2,"move":"tail_whip"},{"klass":"LevelLearnableMove","level":5,"move":"water_sport"},{"klass":"LevelLearnableMove","level":7,"move":"bubble"},{"klass":"LevelLearnableMove","level":10,"move":"defense_curl"},{"klass":"LevelLearnableMove","level":10,"move":"rollout"},{"klass":"LevelLearnableMove","level":13,"move":"bubble_beam"},{"klass":"LevelLearnableMove","level":16,"move":"helping_hand"},{"klass":"LevelLearnableMove","level":20,"move":"aqua_tail"},{"klass":"LevelLearnableMove","level":23,"move":"play_rough"},{"klass":"LevelLearnableMove","level":28,"move":"aqua_ring"},{"klass":"LevelLearnableMove","level":31,"move":"rain_dance"},{"klass":"LevelLearnableMove","level":37,"move":"double_edge"},{"klass":"LevelLearnableMove","level":40,"move":"superpower"},{"klass":"LevelLearnableMove","level":47,"move":"hydro_pump"},{"klass":"TutorLearnableMove","move":"ice_punch"},{"klass":"TutorLearnableMove","move":"snore"},{"klass":"TutorLearnableMove","move":"icy_wind"},{"klass":"TutorLearnableMove","move":"iron_tail"},{"klass":"TutorLearnableMove","move":"focus_punch"},{"klass":"TutorLearnableMove","move":"helping_hand"},{"klass":"TutorLearnableMove","move":"superpower"},{"klass":"TutorLearnableMove","move":"knock_off"},{"klass":"TutorLearnableMove","move":"hyper_voice"},{"klass":"TutorLearnableMove","move":"bounce"},{"klass":"TutorLearnableMove","move":"covet"},{"klass":"TutorLearnableMove","move":"water_pulse"},{"klass":"TutorLearnableMove","move":"aqua_tail"},{"klass":"TechLearnableMove","move":"surf"},{"klass":"TechLearnableMove","move":"ice_beam"},{"klass":"TechLearnableMove","move":"blizzard"},{"klass":"TechLearnableMove","move":"strength"},{"klass":"TechLearnableMove","move":"dig"},{"klass":"TechLearnableMove","move":"toxic"},{"klass":"TechLearnableMove","move":"double_team"},{"klass":"TechLearnableMove","move":"light_screen"},{"klass":"TechLearnableMove","move":"waterfall"},{"klass":"TechLearnableMove","move":"rest"},{"klass":"TechLearnableMove","move":"substitute"},{"klass":"TechLearnableMove","move":"protect"},{"klass":"TechLearnableMove","move":"swagger"},{"klass":"TechLearnableMove","move":"attract"},{"klass":"TechLearnableMove","move":"sleep_talk"},{"klass":"TechLearnableMove","move":"return"},{"klass":"TechLearnableMove","move":"frustration"},{"klass":"TechLearnableMove","move":"hidden_power"},{"klass":"TechLearnableMove","move":"rain_dance"},{"klass":"TechLearnableMove","move":"rock_smash"},{"klass":"TechLearnableMove","move":"hail"},{"klass":"TechLearnableMove","move":"facade"},{"klass":"TechLearnableMove","move":"brick_break"},{"klass":"TechLearnableMove","move":"secret_power"},{"klass":"TechLearnableMove","move":"dive"},{"klass":"TechLearnableMove","move":"fling"},{"klass":"TechLearnableMove","move":"grass_knot"},{"klass":"TechLearnableMove","move":"round"},{"klass":"TechLearnableMove","move":"scald"},{"klass":"TechLearnableMove","move":"confide"},{"klass":"TechLearnableMove","move":"power_up_punch"},{"klass":"BreedLearnableMove","move":"body_slam"},{"klass":"BreedLearnableMove","move":"supersonic"},{"klass":"BreedLearnableMove","move":"amnesia"},{"klass":"BreedLearnableMove","move":"belly_drum"},{"klass":"BreedLearnableMove","move":"perish_song"},{"klass":"BreedLearnableMove","move":"present"},{"klass":"BreedLearnableMove","move":"future_sight"},{"klass":"BreedLearnableMove","move":"superpower"},{"klass":"BreedLearnableMove","move":"refresh"},{"klass":"BreedLearnableMove","move":"camouflage"},{"klass":"BreedLearnableMove","move":"muddy_water"},{"klass":"BreedLearnableMove","move":"water_sport"},{"klass":"BreedLearnableMove","move":"aqua_jet"}]}],"klass":"Specie"}