{"id":274,"dbSymbol":"nuzleaf","forms":[{"form":0,"height":1.0,"weight":28.0,"type1":"grass","type2":"dark","baseHp":70,"baseAtk":70,"baseDfe":40,"baseSpd":60,"baseAts":60,"baseDfs":40,"evHp":0,"evAtk":2,"evDfe":0,"evSpd":0,"evAts":0,"evDfs":0,"evolutions":[{"conditions":[{"type":"stone","value":"leaf_stone"}],"dbSymbol":"shiftry","form":0}],"experienceType":3,"baseExperience":119,"baseLoyalty":70,"catchRate":120,"femaleRate":50,"breedGroups":[5,7],"hatchSteps":3840,"babyDbSymbol":"seedot","babyForm":0,"itemHeld":[],"abilities":["chlorophyll","early_bird","pickpocket"],"frontOffsetY":20,"moveSet":[{"klass":"LevelLearnableMove","level":1,"move":"pound"},{"klass":"LevelLearnableMove","level":3,"move":"harden"},{"klass":"LevelLearnableMove","level":6,"move":"growth"},{"klass":"LevelLearnableMove","level":9,"move":"nature_power"},{"klass":"LevelLearnableMove","level":12,"move":"fake_out"},{"klass":"LevelLearnableMove","level":14,"move":"razor_leaf"},{"klass":"LevelLearnableMove","level":16,"move":"torment"},{"klass":"LevelLearnableMove","level":20,"move":"razor_wind"},{"klass":"LevelLearnableMove","level":24,"move":"feint_attack"},{"klass":"LevelLearnableMove","level":28,"move":"leaf_blade"},{"klass":"LevelLearnableMove","level":32,"move":"swagger"},{"klass":"LevelLearnableMove","level":36,"move":"extrasensory"},{"klass":"TutorLearnableMove","move":"low_kick"},{"klass":"TutorLearnableMove","move":"snore"},{"klass":"TutorLearnableMove","move":"spite"},{"klass":"TutorLearnableMove","move":"giga_drain"},{"klass":"TutorLearnableMove","move":"synthesis"},{"klass":"TutorLearnableMove","move":"worry_seed"},{"klass":"TutorLearnableMove","move":"seed_bomb"},{"klass":"TutorLearnableMove","move":"foul_play"},{"klass":"TechLearnableMove","move":"swords_dance"},{"klass":"TechLearnableMove","move":"cut"},{"klass":"TechLearnableMove","move":"hyper_beam"},{"klass":"TechLearnableMove","move":"strength"},{"klass":"TechLearnableMove","move":"solar_beam"},{"klass":"TechLearnableMove","move":"dig"},{"klass":"TechLearnableMove","move":"toxic"},{"klass":"TechLearnableMove","move":"double_team"},{"klass":"TechLearnableMove","move":"flash"},{"klass":"TechLearnableMove","move":"explosion"},{"klass":"TechLearnableMove","move":"rest"},{"klass":"TechLearnableMove","move":"rock_slide"},{"klass":"TechLearnableMove","move":"substitute"},{"klass":"TechLearnableMove","move":"thief"},{"klass":"TechLearnableMove","move":"protect"},{"klass":"TechLearnableMove","move":"false_swipe"},{"klass":"TechLearnableMove","move":"swagger"},{"klass":"TechLearnableMove","move":"attract"},{"klass":"TechLearnableMove","move":"sleep_talk"},{"klass":"TechLearnableMove","move":"return"},{"klass":"TechLearnableMove","move":"frustration"},{"klass":"TechLearnableMove","move":"hidden_power"},{"klass":"TechLearnableMove","move":"sunny_day"},{"klass":"TechLearnableMove","move":"psych_up"},{"klass":"TechLearnableMove","move":"shadow_ball"},{"klass":"TechLearnableMove","move":"rock_smash"},{"klass":"TechLearnableMove","move":"torment"},{"klass":"TechLearnableMove","move":"facade"},{"klass":"TechLearnableMove","move":"nature_power"},{"klass":"TechLearnableMove","move":"brick_break"},{"klass":"TechLearnableMove","move":"secret_power"},{"klass":"TechLearnableMove","move":"rock_tomb"},{"klass":"TechLearnableMove","move":"payback"},{"klass":"TechLearnableMove","move":"embargo"},{"klass":"TechLearnableMove","move":"fling"},{"klass":"TechLearnableMove","move":"dark_pulse"},{"klass":"TechLearnableMove","move":"energy_ball"},{"klass":"TechLearnableMove","move":"grass_knot"},{"klass":"TechLearnableMove","move":"low_sweep"},{"klass":"TechLearnableMove","move":"round"},{"klass":"TechLearnableMove","move":"retaliate"},{"klass":"TechLearnableMove","move":"snarl"},{"klass":"TechLearnableMove","move":"confide"},{"klass":"TechLearnableMove","move":"power_up_punch"}]}],"klass":"Specie"}