{"id":16,"dbSymbol":"pidgey","forms":[{"form":0,"height":0.3,"weight":1.8,"type1":"normal","type2":"flying","baseHp":40,"baseAtk":45,"baseDfe":40,"baseSpd":56,"baseAts":35,"baseDfs":35,"evHp":0,"evAtk":0,"evDfe":0,"evSpd":1,"evAts":0,"evDfs":0,"evolutions":[{"conditions":[{"type":"minLevel","value":18}],"dbSymbol":"pidgeotto","form":0}],"experienceType":3,"baseExperience":50,"baseLoyalty":70,"catchRate":255,"femaleRate":50,"breedGroups":[4,4],"hatchSteps":3840,"babyDbSymbol":"pidgey","babyForm":0,"itemHeld":[{"dbSymbol":"none","chance":0},{"dbSymbol":"none","chance":0}],"abilities":["keen_eye","tangled_feet","big_pecks"],"frontOffsetY":27,"moveSet":[{"klass":"LevelLearnableMove","level":1,"move":"tackle"},{"klass":"LevelLearnableMove","level":5,"move":"sand_attack"},{"klass":"LevelLearnableMove","level":9,"move":"gust"},{"klass":"LevelLearnableMove","level":13,"move":"quick_attack"},{"klass":"LevelLearnableMove","level":17,"move":"whirlwind"},{"klass":"LevelLearnableMove","level":21,"move":"twister"},{"klass":"LevelLearnableMove","level":25,"move":"feather_dance"},{"klass":"LevelLearnableMove","level":29,"move":"agility"},{"klass":"LevelLearnableMove","level":33,"move":"wing_attack"},{"klass":"LevelLearnableMove","level":37,"move":"roost"},{"klass":"LevelLearnableMove","level":41,"move":"tailwind"},{"klass":"LevelLearnableMove","level":45,"move":"mirror_move"},{"klass":"LevelLearnableMove","level":49,"move":"air_slash"},{"klass":"LevelLearnableMove","level":53,"move":"hurricane"},{"klass":"TutorLearnableMove","move":"sky_attack"},{"klass":"TutorLearnableMove","move":"snore"},{"klass":"TutorLearnableMove","move":"uproar"},{"klass":"TutorLearnableMove","move":"heat_wave"},{"klass":"TutorLearnableMove","move":"tailwind"},{"klass":"TechLearnableMove","move":"fly"},{"klass":"TechLearnableMove","move":"toxic"},{"klass":"TechLearnableMove","move":"double_team"},{"klass":"TechLearnableMove","move":"rest"},{"klass":"TechLearnableMove","move":"substitute"},{"klass":"TechLearnableMove","move":"thief"},{"klass":"TechLearnableMove","move":"protect"},{"klass":"TechLearnableMove","move":"swagger"},{"klass":"TechLearnableMove","move":"steel_wing"},{"klass":"TechLearnableMove","move":"attract"},{"klass":"TechLearnableMove","move":"sleep_talk"},{"klass":"TechLearnableMove","move":"return"},{"klass":"TechLearnableMove","move":"frustration"},{"klass":"TechLearnableMove","move":"hidden_power"},{"klass":"TechLearnableMove","move":"rain_dance"},{"klass":"TechLearnableMove","move":"sunny_day"},{"klass":"TechLearnableMove","move":"facade"},{"klass":"TechLearnableMove","move":"secret_power"},{"klass":"TechLearnableMove","move":"aerial_ace"},{"klass":"TechLearnableMove","move":"roost"},{"klass":"TechLearnableMove","move":"u_turn"},{"klass":"TechLearnableMove","move":"round"},{"klass":"TechLearnableMove","move":"confide"},{"klass":"BreedLearnableMove","move":"feint_attack"},{"klass":"BreedLearnableMove","move":"foresight"},{"klass":"BreedLearnableMove","move":"steel_wing"},{"klass":"BreedLearnableMove","move":"pursuit"},{"klass":"BreedLearnableMove","move":"uproar"},{"klass":"BreedLearnableMove","move":"air_cutter"},{"klass":"BreedLearnableMove","move":"air_slash"},{"klass":"BreedLearnableMove","move":"brave_bird"},{"klass":"BreedLearnableMove","move":"defog"}]}],"klass":"Specie"}