{"id":378,"dbSymbol":"regice","forms":[{"form":0,"height":1.8,"weight":175.0,"type1":"ice","type2":"__undef__","baseHp":80,"baseAtk":50,"baseDfe":100,"baseSpd":50,"baseAts":100,"baseDfs":200,"evHp":0,"evAtk":0,"evDfe":0,"evSpd":0,"evAts":0,"evDfs":3,"evolutions":[],"experienceType":2,"baseExperience":261,"baseLoyalty":35,"catchRate":3,"femaleRate":-1,"breedGroups":[15,15],"hatchSteps":20480,"babyDbSymbol":"__undef__","babyForm":0,"itemHeld":[],"abilities":["clear_body","clear_body","ice_body"],"frontOffsetY":15,"moveSet":[{"klass":"LevelLearnableMove","level":1,"move":"explosion"},{"klass":"LevelLearnableMove","level":1,"move":"stomp"},{"klass":"LevelLearnableMove","level":1,"move":"icy_wind"},{"klass":"LevelLearnableMove","level":1,"move":"charge_beam"},{"klass":"LevelLearnableMove","level":1,"move":"bulldoze"},{"klass":"LevelLearnableMove","level":7,"move":"icy_wind"},{"klass":"LevelLearnableMove","level":13,"move":"charge_beam"},{"klass":"LevelLearnableMove","level":19,"move":"bulldoze"},{"klass":"LevelLearnableMove","level":25,"move":"curse"},{"klass":"LevelLearnableMove","level":31,"move":"ancient_power"},{"klass":"LevelLearnableMove","level":37,"move":"amnesia"},{"klass":"LevelLearnableMove","level":43,"move":"ice_beam"},{"klass":"LevelLearnableMove","level":49,"move":"hammer_arm"},{"klass":"LevelLearnableMove","level":55,"move":"lock_on"},{"klass":"LevelLearnableMove","level":55,"move":"zap_cannon"},{"klass":"LevelLearnableMove","level":61,"move":"superpower"},{"klass":"LevelLearnableMove","level":67,"move":"hyper_beam"},{"klass":"TutorLearnableMove","move":"ice_punch"},{"klass":"TutorLearnableMove","move":"thunder_punch"},{"klass":"TutorLearnableMove","move":"snore"},{"klass":"TutorLearnableMove","move":"icy_wind"},{"klass":"TutorLearnableMove","move":"focus_punch"},{"klass":"TutorLearnableMove","move":"superpower"},{"klass":"TutorLearnableMove","move":"signal_beam"},{"klass":"TutorLearnableMove","move":"block"},{"klass":"TutorLearnableMove","move":"shock_wave"},{"klass":"TutorLearnableMove","move":"gravity"},{"klass":"TutorLearnableMove","move":"iron_head"},{"klass":"TechLearnableMove","move":"ice_beam"},{"klass":"TechLearnableMove","move":"blizzard"},{"klass":"TechLearnableMove","move":"hyper_beam"},{"klass":"TechLearnableMove","move":"strength"},{"klass":"TechLearnableMove","move":"thunderbolt"},{"klass":"TechLearnableMove","move":"thunder_wave"},{"klass":"TechLearnableMove","move":"thunder"},{"klass":"TechLearnableMove","move":"earthquake"},{"klass":"TechLearnableMove","move":"toxic"},{"klass":"TechLearnableMove","move":"double_team"},{"klass":"TechLearnableMove","move":"explosion"},{"klass":"TechLearnableMove","move":"rest"},{"klass":"TechLearnableMove","move":"rock_slide"},{"klass":"TechLearnableMove","move":"substitute"},{"klass":"TechLearnableMove","move":"protect"},{"klass":"TechLearnableMove","move":"swagger"},{"klass":"TechLearnableMove","move":"sleep_talk"},{"klass":"TechLearnableMove","move":"return"},{"klass":"TechLearnableMove","move":"frustration"},{"klass":"TechLearnableMove","move":"safeguard"},{"klass":"TechLearnableMove","move":"hidden_power"},{"klass":"TechLearnableMove","move":"rain_dance"},{"klass":"TechLearnableMove","move":"psych_up"},{"klass":"TechLearnableMove","move":"rock_smash"},{"klass":"TechLearnableMove","move":"hail"},{"klass":"TechLearnableMove","move":"facade"},{"klass":"TechLearnableMove","move":"brick_break"},{"klass":"TechLearnableMove","move":"secret_power"},{"klass":"TechLearnableMove","move":"rock_tomb"},{"klass":"TechLearnableMove","move":"fling"},{"klass":"TechLearnableMove","move":"rock_polish"},{"klass":"TechLearnableMove","move":"focus_blast"},{"klass":"TechLearnableMove","move":"giga_impact"},{"klass":"TechLearnableMove","move":"flash_cannon"},{"klass":"TechLearnableMove","move":"charge_beam"},{"klass":"TechLearnableMove","move":"round"},{"klass":"TechLearnableMove","move":"bulldoze"},{"klass":"TechLearnableMove","move":"frost_breath"},{"klass":"TechLearnableMove","move":"confide"},{"klass":"TechLearnableMove","move":"power_up_punch"}]}],"klass":"Specie"}