{"id":121,"dbSymbol":"starmie","forms":[{"form":0,"height":1.1,"weight":80.0,"type1":"water","type2":"psychic","baseHp":60,"baseAtk":75,"baseDfe":85,"baseSpd":115,"baseAts":100,"baseDfs":85,"evHp":0,"evAtk":0,"evDfe":0,"evSpd":2,"evAts":0,"evDfs":0,"evolutions":[],"experienceType":2,"baseExperience":182,"baseLoyalty":70,"catchRate":60,"femaleRate":-1,"breedGroups":[9,9],"hatchSteps":5120,"babyDbSymbol":"staryu","babyForm":0,"itemHeld":[{"dbSymbol":"none","chance":0},{"dbSymbol":"none","chance":0}],"abilities":["natural_cure","illuminate","analytic"],"frontOffsetY":22,"moveSet":[{"klass":"LevelLearnableMove","level":1,"move":"hydro_pump"},{"klass":"LevelLearnableMove","level":1,"move":"water_gun"},{"klass":"LevelLearnableMove","level":1,"move":"rapid_spin"},{"klass":"LevelLearnableMove","level":1,"move":"recover"},{"klass":"LevelLearnableMove","level":1,"move":"swift"},{"klass":"LevelLearnableMove","level":40,"move":"confuse_ray"},{"klass":"TutorLearnableMove","move":"snore"},{"klass":"TutorLearnableMove","move":"icy_wind"},{"klass":"TutorLearnableMove","move":"pain_split"},{"klass":"TutorLearnableMove","move":"trick"},{"klass":"TutorLearnableMove","move":"magic_coat"},{"klass":"TutorLearnableMove","move":"recycle"},{"klass":"TutorLearnableMove","move":"skill_swap"},{"klass":"TutorLearnableMove","move":"signal_beam"},{"klass":"TutorLearnableMove","move":"water_pulse"},{"klass":"TutorLearnableMove","move":"gravity"},{"klass":"TutorLearnableMove","move":"wonder_room"},{"klass":"TechLearnableMove","move":"surf"},{"klass":"TechLearnableMove","move":"ice_beam"},{"klass":"TechLearnableMove","move":"blizzard"},{"klass":"TechLearnableMove","move":"hyper_beam"},{"klass":"TechLearnableMove","move":"thunderbolt"},{"klass":"TechLearnableMove","move":"thunder_wave"},{"klass":"TechLearnableMove","move":"thunder"},{"klass":"TechLearnableMove","move":"toxic"},{"klass":"TechLearnableMove","move":"psychic"},{"klass":"TechLearnableMove","move":"double_team"},{"klass":"TechLearnableMove","move":"light_screen"},{"klass":"TechLearnableMove","move":"reflect"},{"klass":"TechLearnableMove","move":"waterfall"},{"klass":"TechLearnableMove","move":"dream_eater"},{"klass":"TechLearnableMove","move":"flash"},{"klass":"TechLearnableMove","move":"rest"},{"klass":"TechLearnableMove","move":"substitute"},{"klass":"TechLearnableMove","move":"protect"},{"klass":"TechLearnableMove","move":"swagger"},{"klass":"TechLearnableMove","move":"sleep_talk"},{"klass":"TechLearnableMove","move":"return"},{"klass":"TechLearnableMove","move":"frustration"},{"klass":"TechLearnableMove","move":"hidden_power"},{"klass":"TechLearnableMove","move":"rain_dance"},{"klass":"TechLearnableMove","move":"psych_up"},{"klass":"TechLearnableMove","move":"hail"},{"klass":"TechLearnableMove","move":"facade"},{"klass":"TechLearnableMove","move":"secret_power"},{"klass":"TechLearnableMove","move":"dive"},{"klass":"TechLearnableMove","move":"gyro_ball"},{"klass":"TechLearnableMove","move":"giga_impact"},{"klass":"TechLearnableMove","move":"flash_cannon"},{"klass":"TechLearnableMove","move":"trick_room"},{"klass":"TechLearnableMove","move":"grass_knot"},{"klass":"TechLearnableMove","move":"psyshock"},{"klass":"TechLearnableMove","move":"round"},{"klass":"TechLearnableMove","move":"scald"},{"klass":"TechLearnableMove","move":"confide"},{"klass":"TechLearnableMove","move":"dazzling_gleam"}]}],"klass":"Specie"}