{"id":73,"dbSymbol":"tentacruel","forms":[{"form":0,"height":1.6,"weight":55.0,"type1":"water","type2":"poison","baseHp":80,"baseAtk":70,"baseDfe":65,"baseSpd":100,"baseAts":80,"baseDfs":120,"evHp":0,"evAtk":0,"evDfe":0,"evSpd":0,"evAts":0,"evDfs":2,"evolutions":[],"experienceType":2,"baseExperience":180,"baseLoyalty":70,"catchRate":60,"femaleRate":50,"breedGroups":[9,9],"hatchSteps":5120,"babyDbSymbol":"tentacool","babyForm":0,"itemHeld":[{"dbSymbol":"none","chance":0},{"dbSymbol":"none","chance":0}],"abilities":["clear_body","liquid_ooze","rain_dish"],"frontOffsetY":16,"moveSet":[{"klass":"LevelLearnableMove","level":1,"move":"reflect_type"},{"klass":"LevelLearnableMove","level":1,"move":"wring_out"},{"klass":"LevelLearnableMove","level":1,"move":"poison_sting"},{"klass":"LevelLearnableMove","level":1,"move":"supersonic"},{"klass":"LevelLearnableMove","level":1,"move":"constrict"},{"klass":"LevelLearnableMove","level":1,"move":"acid"},{"klass":"LevelLearnableMove","level":4,"move":"supersonic"},{"klass":"LevelLearnableMove","level":7,"move":"constrict"},{"klass":"LevelLearnableMove","level":10,"move":"acid"},{"klass":"LevelLearnableMove","level":13,"move":"toxic_spikes"},{"klass":"LevelLearnableMove","level":16,"move":"water_pulse"},{"klass":"LevelLearnableMove","level":19,"move":"wrap"},{"klass":"LevelLearnableMove","level":22,"move":"acid_spray"},{"klass":"LevelLearnableMove","level":25,"move":"bubble_beam"},{"klass":"LevelLearnableMove","level":28,"move":"barrier"},{"klass":"LevelLearnableMove","level":32,"move":"poison_jab"},{"klass":"LevelLearnableMove","level":36,"move":"brine"},{"klass":"LevelLearnableMove","level":40,"move":"screech"},{"klass":"LevelLearnableMove","level":44,"move":"hex"},{"klass":"LevelLearnableMove","level":48,"move":"sludge_wave"},{"klass":"LevelLearnableMove","level":52,"move":"hydro_pump"},{"klass":"LevelLearnableMove","level":56,"move":"wring_out"},{"klass":"TutorLearnableMove","move":"bind"},{"klass":"TutorLearnableMove","move":"snore"},{"klass":"TutorLearnableMove","move":"icy_wind"},{"klass":"TutorLearnableMove","move":"giga_drain"},{"klass":"TutorLearnableMove","move":"magic_coat"},{"klass":"TutorLearnableMove","move":"knock_off"},{"klass":"TutorLearnableMove","move":"water_pulse"},{"klass":"TechLearnableMove","move":"swords_dance"},{"klass":"TechLearnableMove","move":"cut"},{"klass":"TechLearnableMove","move":"surf"},{"klass":"TechLearnableMove","move":"ice_beam"},{"klass":"TechLearnableMove","move":"blizzard"},{"klass":"TechLearnableMove","move":"hyper_beam"},{"klass":"TechLearnableMove","move":"toxic"},{"klass":"TechLearnableMove","move":"double_team"},{"klass":"TechLearnableMove","move":"waterfall"},{"klass":"TechLearnableMove","move":"rest"},{"klass":"TechLearnableMove","move":"substitute"},{"klass":"TechLearnableMove","move":"thief"},{"klass":"TechLearnableMove","move":"protect"},{"klass":"TechLearnableMove","move":"sludge_bomb"},{"klass":"TechLearnableMove","move":"swagger"},{"klass":"TechLearnableMove","move":"attract"},{"klass":"TechLearnableMove","move":"sleep_talk"},{"klass":"TechLearnableMove","move":"return"},{"klass":"TechLearnableMove","move":"frustration"},{"klass":"TechLearnableMove","move":"safeguard"},{"klass":"TechLearnableMove","move":"hidden_power"},{"klass":"TechLearnableMove","move":"rain_dance"},{"klass":"TechLearnableMove","move":"hail"},{"klass":"TechLearnableMove","move":"facade"},{"klass":"TechLearnableMove","move":"secret_power"},{"klass":"TechLearnableMove","move":"dive"},{"klass":"TechLearnableMove","move":"payback"},{"klass":"TechLearnableMove","move":"poison_jab"},{"klass":"TechLearnableMove","move":"giga_impact"},{"klass":"TechLearnableMove","move":"venoshock"},{"klass":"TechLearnableMove","move":"sludge_wave"},{"klass":"TechLearnableMove","move":"round"},{"klass":"TechLearnableMove","move":"scald"},{"klass":"TechLearnableMove","move":"confide"},{"klass":"TechLearnableMove","move":"dazzling_gleam"},{"klass":"TechLearnableMove","move":"infestation"}]}],"klass":"Specie"}