{"id":571,"dbSymbol":"zoroark","forms":[{"form":0,"height":1.6,"weight":81.1,"type1":"dark","type2":"__undef__","baseHp":60,"baseAtk":105,"baseDfe":60,"baseSpd":105,"baseAts":120,"baseDfs":60,"evHp":0,"evAtk":0,"evDfe":0,"evSpd":0,"evAts":2,"evDfs":0,"evolutions":[],"experienceType":3,"baseExperience":179,"baseLoyalty":70,"catchRate":45,"femaleRate":12,"breedGroups":[5,5],"hatchSteps":6400,"babyDbSymbol":"zorua","babyForm":0,"itemHeld":[],"abilities":["illusion","illusion","illusion"],"frontOffsetY":16,"moveSet":[{"klass":"LevelLearnableMove","level":1,"move":"night_daze"},{"klass":"LevelLearnableMove","level":1,"move":"imprison"},{"klass":"LevelLearnableMove","level":1,"move":"u_turn"},{"klass":"LevelLearnableMove","level":1,"move":"scratch"},{"klass":"LevelLearnableMove","level":1,"move":"leer"},{"klass":"LevelLearnableMove","level":1,"move":"pursuit"},{"klass":"LevelLearnableMove","level":1,"move":"hone_claws"},{"klass":"LevelLearnableMove","level":5,"move":"pursuit"},{"klass":"LevelLearnableMove","level":9,"move":"hone_claws"},{"klass":"LevelLearnableMove","level":13,"move":"fury_swipes"},{"klass":"LevelLearnableMove","level":17,"move":"feint_attack"},{"klass":"LevelLearnableMove","level":21,"move":"scary_face"},{"klass":"LevelLearnableMove","level":25,"move":"taunt"},{"klass":"LevelLearnableMove","level":29,"move":"foul_play"},{"klass":"LevelLearnableMove","level":30,"move":"night_slash"},{"klass":"LevelLearnableMove","level":34,"move":"torment"},{"klass":"LevelLearnableMove","level":39,"move":"agility"},{"klass":"LevelLearnableMove","level":44,"move":"embargo"},{"klass":"LevelLearnableMove","level":49,"move":"punishment"},{"klass":"LevelLearnableMove","level":54,"move":"nasty_plot"},{"klass":"LevelLearnableMove","level":59,"move":"imprison"},{"klass":"LevelLearnableMove","level":64,"move":"night_daze"},{"klass":"TutorLearnableMove","move":"low_kick"},{"klass":"TutorLearnableMove","move":"snore"},{"klass":"TutorLearnableMove","move":"spite"},{"klass":"TutorLearnableMove","move":"uproar"},{"klass":"TutorLearnableMove","move":"trick"},{"klass":"TutorLearnableMove","move":"knock_off"},{"klass":"TutorLearnableMove","move":"snatch"},{"klass":"TutorLearnableMove","move":"hyper_voice"},{"klass":"TutorLearnableMove","move":"bounce"},{"klass":"TutorLearnableMove","move":"covet"},{"klass":"TutorLearnableMove","move":"foul_play"},{"klass":"TechLearnableMove","move":"swords_dance"},{"klass":"TechLearnableMove","move":"cut"},{"klass":"TechLearnableMove","move":"roar"},{"klass":"TechLearnableMove","move":"flamethrower"},{"klass":"TechLearnableMove","move":"hyper_beam"},{"klass":"TechLearnableMove","move":"dig"},{"klass":"TechLearnableMove","move":"toxic"},{"klass":"TechLearnableMove","move":"double_team"},{"klass":"TechLearnableMove","move":"rest"},{"klass":"TechLearnableMove","move":"substitute"},{"klass":"TechLearnableMove","move":"thief"},{"klass":"TechLearnableMove","move":"protect"},{"klass":"TechLearnableMove","move":"swagger"},{"klass":"TechLearnableMove","move":"attract"},{"klass":"TechLearnableMove","move":"sleep_talk"},{"klass":"TechLearnableMove","move":"return"},{"klass":"TechLearnableMove","move":"frustration"},{"klass":"TechLearnableMove","move":"hidden_power"},{"klass":"TechLearnableMove","move":"rain_dance"},{"klass":"TechLearnableMove","move":"sunny_day"},{"klass":"TechLearnableMove","move":"psych_up"},{"klass":"TechLearnableMove","move":"shadow_ball"},{"klass":"TechLearnableMove","move":"rock_smash"},{"klass":"TechLearnableMove","move":"torment"},{"klass":"TechLearnableMove","move":"facade"},{"klass":"TechLearnableMove","move":"taunt"},{"klass":"TechLearnableMove","move":"secret_power"},{"klass":"TechLearnableMove","move":"aerial_ace"},{"klass":"TechLearnableMove","move":"calm_mind"},{"klass":"TechLearnableMove","move":"u_turn"},{"klass":"TechLearnableMove","move":"payback"},{"klass":"TechLearnableMove","move":"embargo"},{"klass":"TechLearnableMove","move":"fling"},{"klass":"TechLearnableMove","move":"dark_pulse"},{"klass":"TechLearnableMove","move":"focus_blast"},{"klass":"TechLearnableMove","move":"giga_impact"},{"klass":"TechLearnableMove","move":"shadow_claw"},{"klass":"TechLearnableMove","move":"grass_knot"},{"klass":"TechLearnableMove","move":"hone_claws"},{"klass":"TechLearnableMove","move":"low_sweep"},{"klass":"TechLearnableMove","move":"round"},{"klass":"TechLearnableMove","move":"incinerate"},{"klass":"TechLearnableMove","move":"retaliate"},{"klass":"TechLearnableMove","move":"snarl"},{"klass":"TechLearnableMove","move":"confide"}]}],"klass":"Specie"}