{"id":372,"dbSymbol":"assurance","klass":"Move","mapUse":0,"type":"dark","power":60,"accuracy":100,"pp":10,"category":"physical","movecriticalRate":1,"battleEngineMethod":"s_assurance","priority":0,"isDirect":true,"isCharge":false,"isRecharge":false,"isBlocable":true,"isSnatchable":false,"isMirrorMove":true,"isPunch":false,"isGravity":false,"isMagicCoatAffected":false,"isUnfreeze":false,"isSoundAttack":false,"isDistance":false,"isHeal":false,"isAuthentic":false,"isBite":false,"isPulse":false,"isBallistics":false,"isMental":false,"isNonSkyBattle":false,"isDance":false,"isKingRockUtility":true,"isPowder":false,"effectChance":0,"battleEngineAimedTarget":"adjacent_pokemon","battleStageMod":[],"moveStatus":[]}