{"id":422,"dbSymbol":"thunder_fang","klass":"Move","mapUse":0,"type":"electric","power":65,"accuracy":95,"pp":15,"category":"physical","movecriticalRate":1,"battleEngineMethod":"s_a_fang","priority":0,"isDirect":true,"isCharge":false,"isRecharge":false,"isBlocable":true,"isSnatchable":false,"isMirrorMove":true,"isPunch":false,"isGravity":false,"isMagicCoatAffected":false,"isUnfreeze":false,"isSoundAttack":false,"isDistance":false,"isHeal":false,"isAuthentic":false,"isBite":true,"isPulse":false,"isBallistics":false,"isMental":false,"isNonSkyBattle":false,"isDance":false,"isKingRockUtility":true,"isPowder":false,"effectChance":10,"battleEngineAimedTarget":"adjacent_pokemon","battleStageMod":[],"moveStatus":[{"status":"PARALYZED","luckRate":10}]}